pytest_affected-0.1.6.dist-info/METADATA
pytest_affected-0.1.6.dist-info/WHEEL
pytest_affected/store.py
pytest_affected/__init__.py
pytest_affected/plugin.py
pytest_affected/_lib.cpython-311-powerpc64le-linux-gnu.so
pytest_affected-0.1.6.dist-info/RECORD
